MANIFEST.in
README.rst
setup.py
docs/CHANGELOG.rst
docs/LICENSE.rst
docs/api.rst
docs/conf.py
docs/glossary.rst
docs/index.rst
docs/_static/.gitkeep
docs/_static/add-maracas-portlet.png
docs/_static/maracas-macros.png
rt/__init__.py
rt.maracas.egg-info/PKG-INFO
rt.maracas.egg-info/SOURCES.txt
rt.maracas.egg-info/dependency_links.txt
rt.maracas.egg-info/entry_points.txt
rt.maracas.egg-info/namespace_packages.txt
rt.maracas.egg-info/not-zip-safe
rt.maracas.egg-info/requires.txt
rt.maracas.egg-info/top_level.txt
rt/maracas/__init__.py
rt/maracas/configure.zcml
rt/maracas/interfaces.py
rt/maracas/testing.py
rt/maracas/Extensions/install.py
rt/maracas/browser/__init__.py
rt/maracas/browser/configure.zcml
rt/maracas/browser/static/.gitkeep
rt/maracas/browser/static/rt-maracas-banner.png
rt/maracas/browser/static/rt-maracas-square.png
rt/maracas/browser/templates/maracas-and-whistle.pt
rt/maracas/browser/templates/maracas-simple.pt
rt/maracas/browser/templates/maracas_macros.pt
rt/maracas/portlets/__init__.py
rt/maracas/portlets/base.pt
rt/maracas/portlets/base.py
rt/maracas/portlets/configure.zcml
rt/maracas/profiles/default/browserlayer.xml
rt/maracas/profiles/default/metadata.xml
rt/maracas/profiles/default/portlets.xml
rt/maracas/profiles/uninstall/browserlayer.xml
rt/maracas/profiles/uninstall/portlets.xml
rt/maracas/tests/__init__.py
rt/maracas/tests/test_setup.py
rt/maracas/upgrades/__init__.py
rt/maracas/upgrades/configure.zcml