Metadata-Version: 1.1
Name: rt.maracas
Version: 0.9.0
Summary: A Plone gadget for the 2014 FIFA World Cup Brazil
Home-page: http://pypi.python.org/pypi/rt.maracas
Author: RedTurtle Technology
Author-email: sviluppoplone@redturtle.it
License: GPL
Keywords: Plone
Platform: UNKNOWN
Classifier: Framework :: Plone
Classifier: Programming Language :: Python
Classifier: License :: OSI Approved :: GNU General Public License (GPL)
